{"cameraMode":{"drawMode":0,"name":"Shaded","section":"Shading Mode"},"sceneLighting":true,"audioPlay":false,"sceneViewState":{"m_AlwaysRefresh":false,"showFog":true,"showSkybox":true,"showFlares":true,"showImageEffects":true,"showParticleSystems":true,"showVisualEffectGraphs":true,"m_FxEnabled":true},"in2DMode":false,"pivot":{"x":135.14076232910157,"y":-50.443382263183597,"z":69.13729858398438},"rotation":{"x":0.24820108711719514,"y":0.10405229032039643,"z":-0.026896754279732705,"w":0.9627823233604431},"size":147.6942901611328,"orthographic":false}